[{"id": "13", "short_name": "ДЭ 13-24", "degree": 1, "institute": "Институт экономики и управления АПК"}, {"id": "08", "short_name": "ДЭ 08-24", "degree": 1, "institute": "Институт экономики и управления АПК"}, {"id": "05", "short_name": "ДЭ 05-24", "degree": 1, "institute": "Институт экономики и управления АПК"}, {"id": "12", "short_name": "ДЭ 12-24", "degree": 1, "institute": "Институт экономики и управления АПК"}, {"id": "11", "short_name": "ДЭ 11-24", "degree": 1, "institute": "Институт экономики и управления АПК"}, {"id": "10", "short_name": "ДЭ 10-24", "degree": 1, "institute": "Институт экономики и управления АПК"}, {"id": "07", "short_name": "ДЭ 07-24", "degree": 1, "institute": "Институт экономики и управления АПК"}, {"id": "06", "short_name": "ДЭ 06-24", "degree": 1, "institute": "Институт экономики и управления АПК"}, {"id": "04", "short_name": "ДЭ 04-24", "degree": 1, "institute": "Институт экономики и управления АПК"}, {"id": "03", "short_name": "ДЭ 03-24", "degree": 1, "institute": "Институт экономики и управления АПК"}, {"id": "02", "short_name": "ДЭ 02-24", "degree": 1, "institute": "Институт экономики и управления АПК"}, {"id": "01", "short_name": "ДЭ 01-24", "degree": 1, "institute": "Институт экономики и управления АПК"}, {"id": "18", "short_name": "ДЭ 18-24", "degree": 1, "institute": "Институт экономики и управления АПК"}, {"id": "17", "short_name": "ДЭ 17-24", "degree": 1, "institute": "Институт экономики и управления АПК"}, {"id": "16", "short_name": "ДЭ 16-24", "degree": 1, "institute": "Институт экономики и управления АПК"}, {"id": "15", "short_name": "ДЭ 15-24", "degree": 1, "institute": "Институт экономики и управления АПК"}, {"id": "25", "short_name": "ДЭ 25-24", "degree": 1, "institute": "Институт экономики и управления АПК"}, {"id": "24", "short_name": "ДЭ 24-24", "degree": 1, "institute": "Институт экономики и управления АПК"}, {"id": "23", "short_name": "ДЭ 23-24", "degree": 1, "institute": "Институт экономики и управления АПК"}, {"id": "22", "short_name": "ДЭ 22-24", "degree": 1, "institute": "Институт экономики и управления АПК"}, {"id": "21", "short_name": "ДЭ 21-24", "degree": 1, "institute": "Институт экономики и управления АПК"}]